odoo/addons/tms_account/README.rst
odoo/addons/tms_account/__init__.py
odoo/addons/tms_account/__manifest__.py
odoo/addons/tms_account/data/analytic_plan.xml
odoo/addons/tms_account/i18n/tms_account.pot
odoo/addons/tms_account/models/__init__.py
odoo/addons/tms_account/models/account_analytic_line.py
odoo/addons/tms_account/models/account_analytic_plan.py
odoo/addons/tms_account/models/account_move.py
odoo/addons/tms_account/models/account_move_line.py
odoo/addons/tms_account/models/analytic_account.py
odoo/addons/tms_account/models/hr_expense.py
odoo/addons/tms_account/models/purchase_order_line.py
odoo/addons/tms_account/models/res_config_settings.py
odoo/addons/tms_account/models/sale_order.py
odoo/addons/tms_account/models/sale_order_line.py
odoo/addons/tms_account/models/tms_order.py
odoo/addons/tms_account/models/tms_route.py
odoo/addons/tms_account/readme/CONFIGURE.md
odoo/addons/tms_account/readme/CONTRIBUTORS.md
odoo/addons/tms_account/readme/CREDITS.md
odoo/addons/tms_account/readme/DESCRIPTION.md
odoo/addons/tms_account/readme/INSTALL.md
odoo/addons/tms_account/readme/MAINTAINERS.md
odoo/addons/tms_account/readme/USAGE.md
odoo/addons/tms_account/security/res_groups.xml
odoo/addons/tms_account/static/description/icon.png
odoo/addons/tms_account/static/description/icon.svg
odoo/addons/tms_account/static/description/index.html
odoo/addons/tms_account/views/account_analytic_plan.xml
odoo/addons/tms_account/views/account_move.xml
odoo/addons/tms_account/views/res_config_settings.xml
odoo/addons/tms_account/views/tms_order.xml
odoo/addons/tms_account/views/tms_route.xml
odoo_addon_tms_account-17.0.1.0.0.1.dist-info/METADATA
odoo_addon_tms_account-17.0.1.0.0.1.dist-info/WHEEL
odoo_addon_tms_account-17.0.1.0.0.1.dist-info/top_level.txt
odoo_addon_tms_account-17.0.1.0.0.1.dist-info/RECORD
